funa/__init__.py
funa/data.py
funa-0.0.2.dist-info/METADATA
funa-0.0.2.dist-info/WHEEL
funa-0.0.2.dist-info/licenses/LICENSE
funa-0.0.2.dist-info/RECORD
